correlaidmatplotlib/__init__.py
correlaidmatplotlib/correlaid.mplstyle
correlaidmatplotlib/figure_helpers.py
correlaidmatplotlib-0.1.3.dist-info/LICENSE.md
correlaidmatplotlib-0.1.3.dist-info/METADATA
correlaidmatplotlib-0.1.3.dist-info/WHEEL
correlaidmatplotlib-0.1.3.dist-info/top_level.txt
correlaidmatplotlib-0.1.3.dist-info/RECORD
