Metadata-Version: 2.1
Name: correlaidmatplotlib
Version: 0.1.3
Summary: A matplotlib style sheet following the CorrelAid style guide
Home-page: https://github.com/CorrelAid/correlaid-matplotlib-style
Author: Marcus Voss
Author-email: voss.marcus@gmail.com
License: UNKNOWN
Platform: UNKNOWN
Classifier: Programming Language :: Python :: 3
Classifier: License :: OSI Approved :: MIT License
Classifier: Operating System :: OS Independent
Requires-Python: >=3.6
Requires-Dist: matplotlib
Requires-Dist: seaborn
Requires-Dist: numpy (==1.19.3)
